{
  "name": "Astar",
  "chain": "ASTR",
  "rpc": [],
  "faucets": [],
  "nativeCurrency": {
    "name": "Astar",
    "symbol": "ASTR",
    "decimals": 18
  },
  "infoURL": "https://astar.network/",
  "shortName": "astr",
  "chainId": 592,
  "networkId": 592,
  "icon": "./chain/592/logo.png",
  "explorers": [
    {
      "name": "subscan",
      "url": "https://astar.subscan.io",
      "standard": "none",
      "icon": "subscan"
    },
    {
      "name": "blockscout",
      "url": "https://blockscout.com/astar",
      "icon": "blockscout",
      "standard": "EIP3091"
    }
  ],
  "tvl": 24680460
}