{
  "name": "Sports Chain Network",
  "chain": "SCN",
  "rpc": [],
  "faucets": [],
  "nativeCurrency": {
    "name": "SCN",
    "symbol": "SCN",
    "decimals": 18
  },
  "infoURL": "https://sportschainnetwork.xyz",
  "shortName": "SCN",
  "chainId": 1904,
  "networkId": 1904,
  "icon": {
    "url": "ipfs://QmdW7XfRgeyoaHXEvXp8MaVteonankR32CxhL3K5Yc2uQM",
    "width": 345,
    "height": 321,
    "format": "png"
  },
  "explorers": [
    {
      "name": "blockscout",
      "url": "https://explorer.sportschainnetwork.xyz",
      "standard": "EIP3091"
    }
  ],
  "tvl": 0
}